vsdrba/IFNet_HDv3_v4_0.py
vsdrba/IFNet_HDv3_v4_1.py
vsdrba/IFNet_HDv3_v4_10.py
vsdrba/IFNet_HDv3_v4_11.py
vsdrba/IFNet_HDv3_v4_12.py
vsdrba/IFNet_HDv3_v4_12_lite.py
vsdrba/IFNet_HDv3_v4_13.py
vsdrba/IFNet_HDv3_v4_13_lite.py
vsdrba/IFNet_HDv3_v4_14.py
vsdrba/IFNet_HDv3_v4_14_lite.py
vsdrba/IFNet_HDv3_v4_15.py
vsdrba/IFNet_HDv3_v4_15_lite.py
vsdrba/IFNet_HDv3_v4_16_lite.py
vsdrba/IFNet_HDv3_v4_17.py
vsdrba/IFNet_HDv3_v4_17_lite.py
vsdrba/IFNet_HDv3_v4_18.py
vsdrba/IFNet_HDv3_v4_19.py
vsdrba/IFNet_HDv3_v4_2.py
vsdrba/IFNet_HDv3_v4_20.py
vsdrba/IFNet_HDv3_v4_21.py
vsdrba/IFNet_HDv3_v4_22.py
vsdrba/IFNet_HDv3_v4_22_lite.py
vsdrba/IFNet_HDv3_v4_23.py
vsdrba/IFNet_HDv3_v4_24.py
vsdrba/IFNet_HDv3_v4_25.py
vsdrba/IFNet_HDv3_v4_25_heavy.py
vsdrba/IFNet_HDv3_v4_25_lite.py
vsdrba/IFNet_HDv3_v4_26.py
vsdrba/IFNet_HDv3_v4_26_heavy.py
vsdrba/IFNet_HDv3_v4_3.py
vsdrba/IFNet_HDv3_v4_4.py
vsdrba/IFNet_HDv3_v4_5.py
vsdrba/IFNet_HDv3_v4_6.py
vsdrba/IFNet_HDv3_v4_7.py
vsdrba/IFNet_HDv3_v4_8.py
vsdrba/IFNet_HDv3_v4_9.py
vsdrba/__init__.py
vsdrba/__main__.py
vsdrba/warplayer.py
vsdrba/.ipynb_checkpoints/IFNet_HDv3_v4_16_lite-checkpoint.py
vsdrba/.ipynb_checkpoints/IFNet_HDv3_v4_24-checkpoint.py
vsdrba/.ipynb_checkpoints/IFNet_HDv3_v4_25-checkpoint.py
vsdrba/.ipynb_checkpoints/IFNet_HDv3_v4_26-checkpoint.py
vsdrba/.ipynb_checkpoints/IFNet_HDv3_v4_26_heavy-checkpoint.py
vsdrba/.ipynb_checkpoints/__init__-checkpoint.py
vsdrba/.ipynb_checkpoints/__main__-checkpoint.py
vsdrba/softsplat/softsplat.py
vsdrba/softsplat/softsplat_torch.py
vsdrba-1.0.2.dist-info/METADATA
vsdrba-1.0.2.dist-info/WHEEL
vsdrba-1.0.2.dist-info/licenses/LICENSE
vsdrba-1.0.2.dist-info/RECORD
