Metadata-Version: 2.4
Name: vsdrba
Version: 1.0.2
Summary: DRBA_RIFE function for VapourSynth
Project-URL: Homepage, https://github.com/routineLife1/VS-DRBA
Project-URL: Issues, https://github.com/routineLife1/VS-DRBA/issues
Author-email: routineLife1 <1315176066@qq.com>
License-File: LICENSE
Keywords: DRBA,PyTorch,RIFE,TensorRT,VapourSynth
Classifier: Environment :: GPU :: NVIDIA CUDA
Classifier: License :: OSI Approved :: MIT License
Classifier: Operating System :: OS Independent
Classifier: Programming Language :: Python :: 3
Classifier: Topic :: Multimedia :: Video
Requires-Python: >=3.10
Requires-Dist: numpy
Requires-Dist: requests
Requires-Dist: torch>=2.6.0
Requires-Dist: tqdm
Requires-Dist: vapoursynth>=66
